oidc_jwt_validation/__init__.py
oidc_jwt_validation/authentication.py
oidc_jwt_validation/http_service.py
oidc_jwt_validation/http_singleton.py
oidc_jwt_validation-0.4.2.dist-info/licenses/LICENSE
oidc_jwt_validation-0.4.2.dist-info/METADATA
oidc_jwt_validation-0.4.2.dist-info/WHEEL
oidc_jwt_validation-0.4.2.dist-info/top_level.txt
oidc_jwt_validation-0.4.2.dist-info/RECORD
